xmlcv/__init__.py
xmlcv/cli.py
xmlcv/config.py
xmlcv/converter.py
xmlcv/converter_v2.py
xmlcv/element_processor.py
xmlcv/processors.py
xmlcv/plugins/__init__.py
xmlcv/plugins/base.py
xmlcv/plugins/docx_plugin.py
xmlcv/plugins/html_plugin.py
xmlcv/plugins/markdown_plugin.py
xmlcv/plugins/pdf_plugin.py
xmlcv/plugins/pptx_plugin.py
xmlcv-0.1.0.dist-info/licenses/LICENSE
xmlcv-0.1.0.dist-info/METADATA
xmlcv-0.1.0.dist-info/WHEEL
xmlcv-0.1.0.dist-info/entry_points.txt
xmlcv-0.1.0.dist-info/top_level.txt
xmlcv-0.1.0.dist-info/RECORD
