Metadata-Version: 2.4
Name: xmlcv
Version: 0.1.0
Summary: A flexible XML to document converter with dynamic element processing and plugin system
Home-page: https://github.com/trunghiahoang/xmlcv
Author: Trung Hia Hoang
Author-email: Trung Nghia Hoang <trunghia.hoang@gmail.com>
License: MIT
Project-URL: Homepage, https://github.com/trunghiahoang/xmlcv
Project-URL: Documentation, https://github.com/trunghiahoang/xmlcv#readme
Project-URL: Repository, https://github.com/trunghiahoang/xmlcv
Project-URL: Bug Tracker, https://github.com/trunghiahoang/xmlcv/issues
Project-URL: Changelog, https://github.com/trunghiahoang/xmlcv/blob/main/CHANGELOG.md
Keywords: xml,html,converter,document,format
Classifier: Development Status :: 3 - Alpha
Classifier: Intended Audience :: Developers
Classifier: License :: OSI Approved :: MIT License
Classifier: Programming Language :: Python :: 3
Classifier: Programming Language :: Python :: 3.8
Classifier: Programming Language :: Python :: 3.9
Classifier: Programming Language :: Python :: 3.10
Classifier: Programming Language :: Python :: 3.11
Classifier: Topic :: Text Processing :: Markup :: XML
Classifier: Topic :: Text Processing :: Markup :: HTML
Requires-Python: >=3.8
License-File: LICENSE
Requires-Dist: lxml>=4.9.0
Provides-Extra: pdf
Requires-Dist: weasyprint>=59.0; extra == "pdf"
Provides-Extra: pdfkit
Requires-Dist: pdfkit>=1.0.0; extra == "pdfkit"
Provides-Extra: docx
Requires-Dist: python-docx>=1.0.0; extra == "docx"
Provides-Extra: pptx
Requires-Dist: python-pptx>=0.6.0; extra == "pptx"
Provides-Extra: markdown
Requires-Dist: markdown>=3.4.0; extra == "markdown"
Provides-Extra: all
Requires-Dist: weasyprint>=59.0; extra == "all"
Requires-Dist: python-docx>=1.0.0; extra == "all"
Requires-Dist: python-pptx>=0.6.0; extra == "all"
Requires-Dist: markdown>=3.4.0; extra == "all"
Provides-Extra: dev
Requires-Dist: pytest>=7.0; extra == "dev"
Requires-Dist: pytest-cov>=4.0; extra == "dev"
Requires-Dist: black>=23.0; extra == "dev"
Requires-Dist: flake8>=6.0; extra == "dev"
Dynamic: author
Dynamic: home-page
Dynamic: license-file
Dynamic: requires-python
